{
  "total_books": 24,
  "books": [
    {
      "title": "මොනර පිලේ ශාපය - 2 කොටස",
      "author": "Unknown",
      "link": "https://t.me/pdfstore21/3247",
      "category": "Other"
    },
    {
      "title": "eeca19a9-1ff2-49bf-8b84-43a2c8d341f4 (1)",
      "author": "Unknown",
      "link": "https://t.me/pdfstore21/3246",
      "category": "Other"
    },
    {
      "title": "කුන්ඩලිනී යෝගය",
      "author": "Unknown",
      "link": "https://t.me/pdfstore21/3245",
      "category": "Other"
    },
    {
      "title": "Casteless or Caste-blind Sinhala",
      "author": "Unknown",
      "link": "https://t.me/pdfstore21/3244",
      "category": "Other"
    },
    {
      "title": "ඇහැළ මලට දම් පාටක් චතුරි දමයන්ති ehela malaya dam patak",
      "author": "Unknown",
      "link": "https://t.me/pdfstore21/3243",
      "category": "Other"
    },
    {
      "title": "රිද්ම පූජා , වත්සලා කරැණාරත්න",
      "author": "Unknown",
      "link": "https://t.me/pdfstore21/3242",
      "category": "Other"
    },
    {
      "title": "වත්සලතාවී , වත්සලා කරැණාරත්න",
      "author": "Unknown",
      "link": "https://t.me/pdfstore21/3241",
      "category": "Other"
    },
    {
      "title": "රාවණාගේ උඩ්ඩිශ තන්ත් රය",
      "author": "Unknown",
      "link": "https://t.me/pdfstore21/3240",
      "category": "Other"
    },
    {
      "title": "අද්භූතී රාවණා සොයා",
      "author": "Unknown",
      "link": "https://t.me/pdfstore21/3239",
      "category": "Other"
    },
    {
      "title": "ඒත් මං ආදරෙයි - Eth man Adarei",
      "author": "Unknown",
      "link": "https://t.me/pdfstore21/3238",
      "category": "Other"
    },
    {
      "title": "ලිට්ල් හවුස් 01 වන අරණක කුඩා නිවස",
      "author": "Unknown",
      "link": "https://t.me/pdfstore21/3237",
      "category": "Other"
    },
    {
      "title": "කාන්තාරයෙ කුසුම",
      "author": "Unknown",
      "link": "https://t.me/pdfstore21/3236",
      "category": "Other"
    },
    {
      "title": "ගොළු හදවත",
      "author": "Unknown",
      "link": "https://t.me/pdfstore21/3235",
      "category": "Other"
    },
    {
      "title": "101-Kamatahan-Sanjaya Nirmal-sinhalaebooks.com",
      "author": "Unknown",
      "link": "https://t.me/pdfstore21/3234",
      "category": "Other"
    },
    {
      "title": "සුසුම් සැනසුම් , වත්සලා කරැණාරත්න",
      "author": "Unknown",
      "link": "https://t.me/pdfstore21/3233",
      "category": "Other"
    },
    {
      "title": "මැයි මාර ප්‍රසංගය",
      "author": "Unknown",
      "link": "https://t.me/pdfstore21/3232",
      "category": "Other"
    },
    {
      "title": "මැයි මාර ප්‍රසංගය",
      "author": "Unknown",
      "link": "https://t.me/pdfstore21/3231",
      "category": "Other"
    },
    {
      "title": "Ven Dhammaratana Shunyathawaya",
      "author": "Unknown",
      "link": "https://t.me/pdfstore21/3230",
      "category": "Other"
    },
    {
      "title": "spartacus-howard",
      "author": "Unknown",
      "link": "https://t.me/pdfstore21/3229",
      "category": "Other"
    },
    {
      "title": "දෙවැනි ගැහැණිය",
      "author": "Unknown",
      "link": "https://t.me/pdfstore21/3228",
      "category": "Other"
    },
    {
      "title": "pini beduwata wasntayk new",
      "author": "Unknown",
      "link": "https://t.me/pdfstore21/3227",
      "category": "Other"
    },
    {
      "title": "bakini malata pni wetila",
      "author": "Unknown",
      "link": "https://t.me/pdfstore21/3226",
      "category": "Other"
    },
    {
      "title": "hansa gigirum new",
      "author": "Unknown",
      "link": "https://t.me/pdfstore21/3225",
      "category": "Other"
    },
    {
      "title": "කොග්ගල නිලමේ දෙවෙනි කොටස",
      "author": "Unknown",
      "link": "https://t.me/pdfstore21/3224",
      "category": "Other"
    }
  ],
  "page": 93,
  "total_pages": 213
}