{
  "total_books": 24,
  "books": [
    {
      "title": "Montha Kristho 6",
      "author": "Unknown",
      "link": "https://t.me/pdfstore21/3583",
      "category": "Other"
    },
    {
      "title": "021",
      "author": "Unknown",
      "link": "https://t.me/pdfstore21/3582",
      "category": "Other"
    },
    {
      "title": "022 - 2012 August 12",
      "author": "Unknown",
      "link": "https://t.me/pdfstore21/3581",
      "category": "Other"
    },
    {
      "title": "023",
      "author": "Unknown",
      "link": "https://t.me/pdfstore21/3580",
      "category": "Other"
    },
    {
      "title": "024 - 2012 August 26",
      "author": "Unknown",
      "link": "https://t.me/pdfstore21/3579",
      "category": "Other"
    },
    {
      "title": "025  -  2012 Sept 02",
      "author": "Unknown",
      "link": "https://t.me/pdfstore21/3578",
      "category": "Other"
    },
    {
      "title": "026  -  2012 Sept 16",
      "author": "Unknown",
      "link": "https://t.me/pdfstore21/3577",
      "category": "Other"
    },
    {
      "title": "027  -  2012 Sept 23",
      "author": "Unknown",
      "link": "https://t.me/pdfstore21/3576",
      "category": "Other"
    },
    {
      "title": "028  -  2012 Oct 07",
      "author": "Unknown",
      "link": "https://t.me/pdfstore21/3575",
      "category": "Other"
    },
    {
      "title": "029  -  2012 Oct 14",
      "author": "Unknown",
      "link": "https://t.me/pdfstore21/3574",
      "category": "Other"
    },
    {
      "title": "030  -  2012 October 21",
      "author": "Unknown",
      "link": "https://t.me/pdfstore21/3573",
      "category": "Other"
    },
    {
      "title": "027  -  2012 Sept 23",
      "author": "Unknown",
      "link": "https://t.me/pdfstore21/3572",
      "category": "Other"
    },
    {
      "title": "031  -  2012 Oct 28",
      "author": "Unknown",
      "link": "https://t.me/pdfstore21/3571",
      "category": "Other"
    },
    {
      "title": "032  -  2012 Nov 04",
      "author": "Unknown",
      "link": "https://t.me/pdfstore21/3570",
      "category": "Other"
    },
    {
      "title": "033  -  2012 Nov 18",
      "author": "Unknown",
      "link": "https://t.me/pdfstore21/3569",
      "category": "Other"
    },
    {
      "title": "034  -  2012 Nov 25",
      "author": "Unknown",
      "link": "https://t.me/pdfstore21/3568",
      "category": "Other"
    },
    {
      "title": "035  -  2012 Dec 16",
      "author": "Unknown",
      "link": "https://t.me/pdfstore21/3567",
      "category": "Other"
    },
    {
      "title": "036 -  2012 Dec 23",
      "author": "Unknown",
      "link": "https://t.me/pdfstore21/3566",
      "category": "Other"
    },
    {
      "title": "037  -  2013 January  06",
      "author": "Unknown",
      "link": "https://t.me/pdfstore21/3565",
      "category": "Other"
    },
    {
      "title": "038  -  2013 January 13",
      "author": "Unknown",
      "link": "https://t.me/pdfstore21/3564",
      "category": "Other"
    },
    {
      "title": "039  -  2013 January 20",
      "author": "Unknown",
      "link": "https://t.me/pdfstore21/3563",
      "category": "Other"
    },
    {
      "title": "040  -  2013-02-03",
      "author": "Unknown",
      "link": "https://t.me/pdfstore21/3562",
      "category": "Other"
    },
    {
      "title": "041  -  2013-02-10",
      "author": "Unknown",
      "link": "https://t.me/pdfstore21/3561",
      "category": "Other"
    },
    {
      "title": "043  -  2013-02-24",
      "author": "Unknown",
      "link": "https://t.me/pdfstore21/3560",
      "category": "Other"
    }
  ],
  "page": 79,
  "total_pages": 213
}